ammbt/__init__.py
ammbt/amms/__init__.py
ammbt/amms/base.py
ammbt/amms/dlmm.py
ammbt/amms/univ2.py
ammbt/amms/univ3.py
ammbt/base/__init__.py
ammbt/base/array_wrapper.py
ammbt/base/reshape_fns.py
ammbt/data/__init__.py
ammbt/data/synthetic.py
ammbt/plotting/__init__.py
ammbt/plotting/core.py
ammbt/portfolio/__init__.py
ammbt/portfolio/analytics.py
ammbt/portfolio/base.py
ammbt/portfolio/enums.py
ammbt/utils/__init__.py
ammbt/utils/config.py
ammbt/utils/math.py
ammbt/utils/strategies.py
ammbt-0.1.0.dist-info/licenses/LICENSE
ammbt-0.1.0.dist-info/METADATA
ammbt-0.1.0.dist-info/WHEEL
ammbt-0.1.0.dist-info/top_level.txt
ammbt-0.1.0.dist-info/RECORD
